td_ml_get_segments/__init__.py
td_ml_get_segments/get_segments.py
td_ml_get_segments-0.0.6.dist-info/METADATA
td_ml_get_segments-0.0.6.dist-info/WHEEL
td_ml_get_segments-0.0.6.dist-info/licenses/LICENSE
td_ml_get_segments-0.0.6.dist-info/RECORD
