Metadata-Version: 2.1
Name: td_ml_get_segments
Version: 0.0.6
Summary: A package to get segments
Project-URL: Homepage, https://github.com/treasure-data-ps/td_ml_get_segments
Project-URL: Bug Tracker, https://github.com/treasure-data-ps/td_ml_get_segments
Author-email: Sai Suraj Argula <saisuraj.argula@treasure-data.com>
License: Copyright © 2022 Treasure Data, Inc. (or its affiliates). All rights reserved
License-File: LICENSE
Classifier: Operating System :: OS Independent
Classifier: Programming Language :: Python :: 3
Requires-Python: >=3.8
